genericparser/__init__.py
genericparser/accept_plugins.py
genericparser/genericparser.py
genericparser/plugins/__init__.py
genericparser/plugins/dinamic/__init__.py
genericparser/plugins/dinamic/github.py
genericparser/plugins/domain/generic_class.py
genericparser/plugins/statics/__init__.py
genericparser/plugins/statics/sonarqube.py
genericparser/services/__init__.py
msgram_parser-1.2.1.dist-info/LICENSE
msgram_parser-1.2.1.dist-info/METADATA
msgram_parser-1.2.1.dist-info/WHEEL
msgram_parser-1.2.1.dist-info/top_level.txt
msgram_parser-1.2.1.dist-info/RECORD
