Metadata-Version: 2.1
Name: msgram-parser
Version: 1.2.1
Summary: The msgram Parser is a PyPI library that serves as a repository for parsing metrics, meaning that it provides a collection of tools, functions, and resources specifically designed to handle and extract information from metric data.
Author-email: MeasureSoftGram <measuresoftgram@gmail.com>
License: GNU GENERAL PUBLIC LICENSE
Keywords: parser,measures,quality,algebraic model
Classifier: Environment :: Console
Classifier: License :: OSI Approved :: GNU Affero General Public License v3 or later (AGPLv3+)
Classifier: Natural Language :: Portuguese (Brazilian)
Classifier: Operating System :: OS Independent
Classifier: Programming Language :: Python :: 3.8
Classifier: Topic :: Utilities
Requires-Python: >=3.9
License-File: LICENSE
Requires-Dist: requests >=2.32
Requires-Dist: numpy >=2.0
Requires-Dist: pandas >=2.2
Provides-Extra: dev
Requires-Dist: pytest ; extra == 'dev'
Requires-Dist: pytest-cov ; extra == 'dev'
Requires-Dist: setuptools ; extra == 'dev'
Requires-Dist: wheel ; extra == 'dev'
